chemstruct/__init__.py
chemstruct/atoms.py
chemstruct/bond_lengths.txt
chemstruct/constants.py
chemstruct/masses.txt
chemstruct/par_all36_cgenff.prm
chemstruct/quick.py
chemstruct/tools.py
chemstruct/__pycache__/__init__.cpython-36.pyc
chemstruct/__pycache__/quick.cpython-36.pyc
chemstruct/examples/01_alkane.xyz
chemstruct/examples/__init__.py
chemstruct/examples/ex01.py
chemstruct/examples/ex02.py
chemstruct/examples/ex03.py
chemstruct/examples/rubber.xyz
chemstruct/files/__init__.py
chemstruct/files/charmm.py
chemstruct/files/csv.py
chemstruct/files/lmp.py
chemstruct/files/main.py
chemstruct/files/xyz.py
chemstruct/files/charmm_proof/01_alkane.xyz
chemstruct/files/charmm_proof/01_alkane_proof.xyz
chemstruct/files/charmm_proof/02_alkene.xyz
chemstruct/files/charmm_proof/02_alkene_proof.xyz
chemstruct/files/charmm_proof/04_imine.xyz
chemstruct/files/charmm_proof/04_imine_proof.xyz
chemstruct/files/charmm_proof/05_amide.xyz
chemstruct/files/charmm_proof/05_amide_proof.xyz
chemstruct/files/charmm_proof/06_acid.xyz
chemstruct/files/charmm_proof/06_acid_proof.xyz
chemstruct/files/charmm_proof/07_ester.xyz
chemstruct/files/charmm_proof/07_ester_proof.xyz
chemstruct/files/charmm_proof/08_ether.xyz
chemstruct/files/charmm_proof/08_ether_proof.xyz
chemstruct/files/charmm_proof/09_aldehyde.xyz
chemstruct/files/charmm_proof/09_aldehyde_proof.xyz
chemstruct/files/charmm_proof/10_ketone.xyz
chemstruct/files/charmm_proof/10_ketone_proof.xyz
chemstruct/files/charmm_proof/11_alcohol.xyz
chemstruct/files/charmm_proof/11_alcohol_proof.xyz
chemstruct/files/charmm_proof/12_cyanide.xyz
chemstruct/files/charmm_proof/12_cyanide_proof.xyz
chemstruct/files/charmm_proof/13_guanidine.xyz
chemstruct/files/charmm_proof/13_guanidine_proof.xyz
chemstruct/files/charmm_proof/14_amidine.xyz
chemstruct/files/charmm_proof/14_amidine_proof.xyz
chemstruct/files/charmm_proof/15_amine.xyz
chemstruct/files/charmm_proof/15_amine_proof.xyz
chemstruct/files/charmm_proof/16_CO2.xyz
chemstruct-2019.6.2.dist-info/LICENSE
chemstruct-2019.6.2.dist-info/METADATA
chemstruct-2019.6.2.dist-info/WHEEL
chemstruct-2019.6.2.dist-info/top_level.txt
chemstruct-2019.6.2.dist-info/RECORD
