Metadata-Version: 2.1
Name: chemstruct
Version: 2019.6.2
Summary: Package for chemical structure analysis of atomic files
Home-page: https://github.com/pdemingos/chemstruct
Author: Pedro Guerra Demingos
Author-email: pdemingos@gmail.com
License: UNKNOWN
Platform: UNKNOWN
Classifier: Programming Language :: Python :: 3
